nepse/__init__.py
nepse/stonk.py
nepse-0.1.2.dist-info/METADATA
nepse-0.1.2.dist-info/WHEEL
nepse-0.1.2.dist-info/top_level.txt
nepse-0.1.2.dist-info/RECORD
