Metadata-Version: 2.1
Name: nepse
Version: 0.1.2
Summary: Python Wrapper for Newweb Nepse
Home-page: https://github.com/pyFrappe/nepse
Author: FRAPPÉ (FRAPPÉ#4101)
License: UNKNOWN
Keywords: python,nepse,stock,nepal stock,nepal stock prices,nepse pythonb
Platform: UNKNOWN
Requires-Dist: requests
Requires-Dist: matplotlib
Requires-Dist: pandas
